snitch/__init__.py
snitch/__main__.py
snitch/assets_rc.py
snitch/ocr.py
snitch/player.py
snitch/recorder.py
snitch/settings.py
snitch/snapper.py
snitch/model/__init__.py
snitch/model/eventlist.py
snitch/model/eventproperties.py
snitch/model/list.py
snitch/model/properties.py
snitch/model/snaplist.py
snitch/model/data/__init__.py
snitch/model/data/events.py
snitch/model/data/screenshot.py
snitch/model/data/testcase.py
snitch/tools/__init__.py
snitch/tools/dump_images.py
snitch/tools/dump_text.py
snitch/ui/__init__.py
snitch/ui/about.py
snitch/ui/about_ui.py
snitch/ui/aspect_ratio_pixmap_label.py
snitch/ui/controller.py
snitch/ui/controller_ui.py
snitch/ui/diff.py
snitch/ui/diff_ui.py
snitch/ui/list_manager.py
snitch/ui/list_manager_ui.py
snitch/ui/modifier_picker.py
snitch/ui/modifier_picker_ui.py
snitch/ui/mouse_tracker.py
snitch/ui/settings.py
snitch/ui/settings_ui.py
snitch_ci-0.7.2.dist-info/LICENSE.txt
snitch_ci-0.7.2.dist-info/METADATA
snitch_ci-0.7.2.dist-info/WHEEL
snitch_ci-0.7.2.dist-info/entry_points.txt
snitch_ci-0.7.2.dist-info/top_level.txt
snitch_ci-0.7.2.dist-info/RECORD
