Metadata-Version: 2.1
Name: snitch-ci
Version: 0.7.2
Summary: An input event recorder and player for automatic testing
Home-page: https://gitlab.com/irsn/snitch-ci
Author: Grégory Millasseau
Author-email: gregory@millasseau.fr
License: UNKNOWN
Platform: UNKNOWN
Classifier: Development Status :: 4 - Beta
Classifier: License :: OSI Approved :: GNU General Public License v3 (GPLv3)
Classifier: Natural Language :: English
Classifier: Operating System :: OS Independent
Classifier: Programming Language :: Python :: 3
Classifier: Topic :: Software Development :: Testing
Requires-Dist: PyQt5 (>=5.11.0)
Requires-Dist: pynput (>=1.3.10)
Requires-Dist: pyautogui (>=0.9.36)
Requires-Dist: imutils (>=0.5.2)
Requires-Dist: scipy (>=1.3.0)
Requires-Dist: scikit-image (==0.14.2)
Requires-Dist: opencv-python (>=4.1.1.26)
Requires-Dist: pytesseract (>=0.3.2)
